sagemaker_tidymodels/__init__.py
sagemaker_tidymodels/tidymodels.py
tests/__init__.py
tests/conftest.py
tests/test_framework.py
tests/test_integration.py
tests/test_local_instance.py
tests/train.py
sagemaker_tidymodels-0.1.1.dist-info/LICENSE
sagemaker_tidymodels-0.1.1.dist-info/METADATA
sagemaker_tidymodels-0.1.1.dist-info/WHEEL
sagemaker_tidymodels-0.1.1.dist-info/top_level.txt
sagemaker_tidymodels-0.1.1.dist-info/RECORD
