Metadata-Version: 2.1
Name: sagemaker-tidymodels
Version: 0.1.1
Summary: Sagemaker framework for Tidymodels
Home-page: https://github.com/tmastny/sagemaker-tidymodels
Author: Timothy Mastny
Author-email: tim.mastny@gmail.com
License: MIT
Platform: UNKNOWN
Classifier: Development Status :: 2 - Pre-Alpha
Classifier: Intended Audience :: Developers
Classifier: License :: OSI Approved :: MIT License
Classifier: Natural Language :: English
Classifier: Programming Language :: Python :: 2
Classifier: Programming Language :: Python :: 2.6
Classifier: Programming Language :: Python :: 2.7
Classifier: Programming Language :: Python :: 3
Classifier: Programming Language :: Python :: 3.3
Classifier: Programming Language :: Python :: Implementation :: PyPy
Requires-Dist: sagemaker
